sentinelpricing/__init__.py
sentinelpricing/models/__init__.py
sentinelpricing/models/abstracts.py
sentinelpricing/models/breakdown.py
sentinelpricing/models/datafile.py
sentinelpricing/models/framework.py
sentinelpricing/models/lookuptable.py
sentinelpricing/models/md5hash.py
sentinelpricing/models/model.py
sentinelpricing/models/note.py
sentinelpricing/models/override.py
sentinelpricing/models/pricetest.py
sentinelpricing/models/quote.py
sentinelpricing/models/rate.py
sentinelpricing/models/step.py
sentinelpricing/models/testcase.py
sentinelpricing/models/testsuite.py
sentinelpricing/models/transformation.py
sentinelpricing/models/deprecated/subset.py
sentinelpricing/protocols/protocols.py
sentinelpricing/utils/__init__.py
sentinelpricing/utils/calculations.py
sentinelpricing/utils/deprecated/xmltodict.py
sentinelpricing-0.1.3.dist-info/licenses/LICENSE
sentinelpricing-0.1.3.dist-info/METADATA
sentinelpricing-0.1.3.dist-info/WHEEL
sentinelpricing-0.1.3.dist-info/top_level.txt
sentinelpricing-0.1.3.dist-info/RECORD
