Metadata-Version: 2.4
Name: sentinelpricing
Version: 0.1.3
Summary: Sentinel Pricing Framework
Author-email: Jonathan Pennell <Jonathan@forestandrock.co.uk>
License: MIT License
Classifier: Programming Language :: Python :: 3
Classifier: License :: OSI Approved :: MIT License
Classifier: Operating System :: OS Independent
Requires-Python: >=3.11
License-File: LICENSE
Provides-Extra: dev
Requires-Dist: black; extra == "dev"
Requires-Dist: flake8; extra == "dev"
Requires-Dist: pytest; extra == "dev"
Requires-Dist: mypy; extra == "dev"
Dynamic: license-file
